{
	"pages": [
		{
			"path": "pages/home/index",
			"style": {
				"navigationBarTitleText": "CampusLink",
				"navigationStyle": "custom",
				"navigationBarTextStyle": "white",
				"enablePullDownRefresh": true,
				"backgroundTextStyle": "dark"
			}
		},
		{
			"path": "pages/community/index",
			"style": {
				"navigationBarTitleText": "社区",
				"navigationStyle": "custom",
				"enablePullDownRefresh": false
			}
		},
		{
			"path": "pages/search/result",
			"style": {
				"navigationBarTitleText": "搜索",
				"navigationStyle": "custom",
				"enablePullDownRefresh": false
			}
		},
		{
			"path": "pages/resource/index",
			"style": {
				"navigationBarTitleText": "资源库",
				"navigationStyle": "custom",
				"enablePullDownRefresh": false
			}
		},
		{
			"path": "pages/resource/detail",
			"style": {
				"navigationBarTitleText": "资源详情",
				"navigationStyle": "custom"
			}
		},
		{
			"path": "pages/resource/upload",
			"style": {
				"navigationBarTitleText": "上传资源",
				"navigationStyle": "custom"
			}
		},
		{
			"path": "pages/resource/my",
			"style": {
				"navigationBarTitleText": "我的资源",
				"navigationStyle": "custom",
				"enablePullDownRefresh": true
			}
		},
		{
			"path": "pages/publish/index",
			"style": {
				"navigationBarTitleText": "选择发布类型",
				"navigationStyle": "custom"
			}
		},
		{
			"path": "pages/auth/login",
			"style": {
				"navigationBarTitleText": "登录",
				"navigationStyle": "custom",
				"enablePullDownRefresh": false
			}
		},
		{
			"path": "pages/auth/register",
			"style": {
				"navigationBarTitleText": "注册",
				"navigationStyle": "custom",
				"enablePullDownRefresh": false
			}
		},
		{
			"path": "pages/question/index",
			"style": {
				"navigationBarTitleText": "问答社区",
				"navigationStyle": "custom"
			}
		},
		{
			"path": "pages/recommend/index",
			"style": {
				"navigationBarTitleText": "全部推荐",
				"navigationStyle": "custom"
			}
		},
		{
			"path": "pages/question/ranking",
			"style": {
				"navigationBarTitleText": "热门问答榜",
				"navigationStyle": "custom"
			}
		},
		{
			"path": "pages/question/detail",
			"style": {
				"navigationBarTitleText": "问题详情",
				"navigationStyle": "custom",
				"enablePullDownRefresh": false
			}
		},
		{
			"path": "pages/question/ask",
			"style": {
				"navigationBarTitleText": "提问",
				"navigationStyle": "custom",
				"enablePullDownRefresh": false
			}
		},
		{
			"path": "pages/question/my",
			"style": {
				"navigationBarTitleText": "我的问答",
				"navigationStyle": "custom",
				"enablePullDownRefresh": true
			}
		},
		{
			"path": "pages/club/activity-detail",
			"style": {
				"navigationStyle": "custom"
			}
		},
		{
			"path": "pages/club/activity-list",
			"style": {
				"navigationStyle": "custom",
				"disableScroll": true
			}
		},
		{
			"path": "pages/club/list",
			"style": {
				"navigationStyle": "custom",
				"enablePullDownRefresh": true
			}
		},
		{
			"path": "pages/club/detail",
			"style": {
				"navigationStyle": "custom"
			}
		},
		{
			"path": "pages/club/members",
			"style": {
				"navigationBarTitleText": "社团成员",
				"navigationBarBackgroundColor": "#FFFFFF",
				"enablePullDownRefresh": true,
				"backgroundTextStyle": "dark"
			}
		},
		{
			"path": "pages/club/create",
			"style": {
				"navigationBarTitleText": "创建社团",
				"navigationStyle": "custom"
			}
		},
		{
			"path": "pages/club/publish-activity",
			"style": {
				"navigationBarTitleText": "发布活动",
				"navigationStyle": "custom"
			}
		},
		{
			"path": "pages/club/my-activities",
			"style": {
				"navigationStyle": "custom",
				"disableScroll": true
			}
		},
		{
			"path": "pages/user/index",
			"style": {
				"navigationBarTitleText": "我的",
				"navigationStyle": "custom",
				"enablePullDownRefresh": false,
				"backgroundTextStyle": "dark"
			}
		},
		{
			"path": "pages/user/edit-profile",
			"style": {
				"navigationBarTitleText": "编辑资料",
				"navigationStyle": "custom",
				"backgroundColor": "#F9FAFB"
			}
		},
		{
			"path": "pages/user/favorites",
			"style": {
				"navigationBarTitleText": "我的收藏",
				"navigationStyle": "custom",
				"enablePullDownRefresh": true
			}
		},
		{
			"path": "pages/user/liked-list",
			"style": {
				"navigationBarTitleText": "获赞",
				"navigationStyle": "custom",
				"enablePullDownRefresh": false
			}
		},
		{
			"path": "pages/user/points-history",
			"style": {
				"navigationStyle": "custom",
				"disableScroll": true
			}
		},
		{
			"path": "pages/user/points-mall",
			"style": {
				"navigationBarTitleText": "积分商城",
				"navigationStyle": "custom",
				"enablePullDownRefresh": false,
				"disableScroll": true
			}
		},
		{
			"path": "pages/user/change-password",
			"style": {
				"navigationBarTitleText": "修改密码",
				"navigationBarBackgroundColor": "#FFFFFF"
			}
		},
		{
			"path": "pages/user/badges",
			"style": {
				"navigationBarTitleText": "我的徽章",
				"navigationStyle": "custom",
				"disableScroll": true
			}
		},
		{
			"path": "pages/task/index",
			"style": {
				"navigationBarTitleText": "任务大厅",
				"navigationStyle": "custom",
				"enablePullDownRefresh": true,
				"backgroundTextStyle": "dark"
			}
		},
		{
			"path": "pages/task/detail",
			"style": {
				"navigationBarTitleText": "任务详情",
				"navigationStyle": "custom"
			}
		},
		{
			"path": "pages/task/publish",
			"style": {
				"navigationBarTitleText": "发布任务",
				"navigationStyle": "custom"
			}
		},
		{
			"path": "pages/task/my",
			"style": {
				"navigationBarTitleText": "我的任务",
				"navigationStyle": "custom",
				"enablePullDownRefresh": true,
				"backgroundTextStyle": "dark"
			}
		},
		{
			"path": "pages/notification/index",
			"style": {
				"navigationStyle": "custom",
				"navigationBarTitleText": "通知中心"
			}
		},
		{
			"path": "pages/message/index",
			"style": {
				"navigationBarTitleText": "私信",
				"navigationStyle": "custom",
				"enablePullDownRefresh": true,
				"backgroundTextStyle": "dark"
			}
		},
		{
			"path": "pages/message/chat",
			"style": {
				"navigationBarTitleText": "聊天",
				"navigationStyle": "custom",
				"enablePullDownRefresh": false
			}
		},
		{
			"path": "pages/ai/chat",
			"style": {
				"navigationBarTitleText": "AI 智能助手",
				"navigationStyle": "custom",
				"enablePullDownRefresh": false
			}
		},
		{
			"path": "pages/error/404",
			"style": {
				"navigationBarTitleText": "页面不存在",
				"navigationStyle": "custom"
			}
		},
		{
			"path": "pages/about/index",
			"style": {
				"navigationBarTitleText": "关于我们",
				"navigationStyle": "custom",
				"enablePullDownRefresh": false
			}
		},
		{
			"path": "pages/about/privacy",
			"style": {
				"navigationBarTitleText": "隐私政策",
				"navigationStyle": "custom",
				"enablePullDownRefresh": false
			}
		},
		{
			"path": "pages/about/terms",
			"style": {
				"navigationBarTitleText": "用户协议",
				"navigationStyle": "custom",
				"enablePullDownRefresh": false
			}
		}
	],
	"usingComponents": {},
	"condition": {
		"current": 0,
		"list": [{
			"name": "404",
			"path": "pages/error/404"
		}]
	},
	"easycom": {
		"autoscan": true,
		"custom": {
			"^uni-(.*)": "@dcloudio/uni-ui/lib/uni-$1/uni-$1.vue",
			"^gp-skeleton$": "@/uni_modules/gp-skeleton/components/gp-skeleton/gp-skeleton.vue",
			"^z-paging$": "z-paging/components/z-paging/z-paging.vue",
			"^z-paging-(.*)$": "z-paging/components/z-paging-$1/z-paging-$1.vue",
			"^LazyImage$": "@/components/LazyImage.vue",
			"^SkeletonScreen$": "@/components/SkeletonScreen.vue",
			"^SkeletonCard$": "@/components/SkeletonCard.vue",
			"^SkeletonResourceCard$": "@/components/SkeletonResourceCard.vue"
		}
	},
	"globalStyle": {
		"navigationBarTextStyle": "black",
		"navigationBarTitleText": "CampusLink",
		"navigationBarBackgroundColor": "#FFFFFF",
		"backgroundColor": "#F5F5F5"
	},
	"tabBar": {
		"custom": true,
		"color": "#999999",
		"selectedColor": "#2563EB",
		"backgroundColor": "#FFFFFF",
		"borderStyle": "black",
		"fontSize": "10px",
		"iconWidth": "24px",
		"height": "50px",
		"list": [
			{
				"pagePath": "pages/home/index",
				"iconPath": "static/tabbar/home.png",
				"selectedIconPath": "static/tabbar/home-active.png",
				"text": "首页"
			},
			{
				"pagePath": "pages/resource/index",
				"iconPath": "static/tabbar/resource.png",
				"selectedIconPath": "static/tabbar/resource-active.png",
				"text": "资源"
			},
			{
				"pagePath": "pages/publish/index",
				"iconPath": "static/tabbar/publish.png",
				"selectedIconPath": "static/tabbar/publish-active.png",
				"text": "发布"
			},
			{
				"pagePath": "pages/question/index",
				"iconPath": "static/tabbar/community.png",
				"selectedIconPath": "static/tabbar/community-active.png",
				"text": "问答"
			},
			{
				"pagePath": "pages/user/index",
				"iconPath": "static/tabbar/user.png",
				"selectedIconPath": "static/tabbar/user-active.png",
				"text": "我的"
			}
		]
	}
}
